pykitty/__init__.py
pykitty/cli.py
pykitty/client.py
pykitty/kitty_parser.py
pykitty-0.3.0.dist-info/LICENSE
pykitty-0.3.0.dist-info/METADATA
pykitty-0.3.0.dist-info/WHEEL
pykitty-0.3.0.dist-info/entry_points.txt
pykitty-0.3.0.dist-info/RECORD
